LICENSE
MANIFEST.in
README.rst
setup.cfg
setup.py
cryptographic_fields/__init__.py
cryptographic_fields/fields.py
cryptographic_fields/settings.py
cryptographic_fields/tests.py
cryptographic_fields/management/__init__.py
cryptographic_fields/management/commands/__init__.py
cryptographic_fields/management/commands/generate_encryption_key.py
django_cryptographic_fields_bihealth.egg-info/PKG-INFO
django_cryptographic_fields_bihealth.egg-info/SOURCES.txt
django_cryptographic_fields_bihealth.egg-info/dependency_links.txt
django_cryptographic_fields_bihealth.egg-info/requires.txt
django_cryptographic_fields_bihealth.egg-info/top_level.txt
testapp/__init__.py
testapp/admin.py
testapp/models.py
testapp/tests.py
testapp/urls.py
testapp/migrations/0001_initial.py
testapp/migrations/__init__.py